mein_paket/__init__.py
saudiarabia-1985.8.31.dist-info/METADATA
saudiarabia-1985.8.31.dist-info/WHEEL
saudiarabia-1985.8.31.dist-info/entry_points.txt
saudiarabia-1985.8.31.dist-info/top_level.txt
saudiarabia-1985.8.31.dist-info/RECORD
