Metadata-Version: 2.1
Name: saudiarabia
Version: 1985.8.31
Summary: saudiarabia
Home-page: https://github.com/dukeskardashian
Author: staatsberater
Author-email: staatsberater@instagram.com
